sentinel_server/__init__.py
sentinel_server/__main__.py
sentinel_server/manuf.py
sentinel_server/sentinel.py
sentinel_server/store.py
sentinel_server/tools.py
sentinel_server/db/manuf
sentinel_server/modules/gitegridy/gitegridy.py
sentinel_server/modules/hv/kvm.py
sentinel_server/modules/ipwhois/ipwhois.py
sentinel_server/modules/ps/ps.py
sentinel_server-1.9.6.dist-info/LICENSE
sentinel_server-1.9.6.dist-info/METADATA
sentinel_server-1.9.6.dist-info/WHEEL
sentinel_server-1.9.6.dist-info/entry_points.txt
sentinel_server-1.9.6.dist-info/top_level.txt
sentinel_server-1.9.6.dist-info/RECORD
